DDCO_HACKATHON/register_file.v
module register_file (
    input clk,
    input [2:0] write_address,
    input [7:0] write_data,
    input write_enable,
    input [2:0] read_address,
    output reg [7:0] read_data
);
    reg [7:0] registers [0:7]; // 8 registers of 8-bit size

    always @(posedge clk) begin
        if (write_enable) begin
            registers[write_address] <= write_data; // Write data to register
        end
    end

    always @(*) begin
        read_data = registers[read_address]; // Read data from register
    end
endmodule

DDCO_HACKATHON/alu.v
module alu (
    input [7:0] a,
    input [7:0] b,
    input [1:0] opcode,
    output reg [7:0] result
);
    always @(*) begin
        case (opcode)
            2'b00: result = a & b; // AND
            2'b01: result = a | b; // OR
            2'b10: result = ~(a & b); // NAND
            2'b11: result = ~(a | b); // NOR
            default: result = 8'b00000000; // Default case
        endcase
    end
endmodule

DDCO_HACKATHON/alu_register_concat.v
module alu_register_concat (
    input clk,
    input [7:0] a,
    input [7:0] b,
    input [1:0] opcode,
    input [2:0] write_address,
    input [2:0] read_address,
    input write_enable,
    output [7:0] read_data
);
    wire [7:0] alu_result;

    // Instantiate ALU
    alu alu_inst (
        .a(a),
        .b(b),
        .opcode(opcode),
        .result(alu_result)
    );

    // Instantiate Register File
    register_file register_file_inst (
        .clk(clk),
        .write_address(write_address),
        .write_data(alu_result),
        .write_enable(write_enable),
        .read_address(read_address),
        .read_data(read_data)
    );
endmodule

DDCO_HACKATHON/alu_register_tb.v
`timescale 1ns/1ps

module alu_register_tb;
    reg clk;
    reg [7:0] a, b;
    reg [1:0] opcode;
    reg [2:0] write_address, read_address;
    reg write_enable;
    wire [7:0] read_data;

    // Instantiate the top module
    alu_register_concat dut (
        .clk(clk),
        .a(a),
        .b(b),
        .opcode(opcode),
        .write_address(write_address),
        .read_address(read_address),
        .write_enable(write_enable),
        .read_data(read_data)
    );

    // Clock generation
    initial begin
        clk = 0;
        forever #5 clk = ~clk; // Generate clock with a period of 10 units
    end

    initial begin
        // Test cases
        $dumpfile("alu_register.vcd"); // VCD file generation
        $dumpvars(0, alu_register_tb);

        // Initialize inputs
        a = 8'b10101010; 
        b = 8'b11001100; 
        opcode = 2'b00; // AND operation
        write_address = 3'b000; 
        write_enable = 1;

        #10; // Wait for 10 time units
        write_enable = 0; // Disable writing

        opcode = 2'b01; // OR operation
        write_address = 3'b001; 
        write_enable = 1;

        #10;
        write_enable = 0;

        opcode = 2'b10; // NAND operation
        write_address = 3'b010; 
        write_enable = 1;

        #10;
        write_enable = 0;

        opcode = 2'b11; // NOR operation
        write_address = 3'b011; 
        write_enable = 1;

        #10;
        write_enable = 0;

        // Read operation
        read_address = 3'b000; #5;
        $display("Read Data (AND): %b", read_data);

        read_address = 3'b001; #5;
        $display("Read Data (OR): %b", read_data);

        read_address = 3'b010; #5;
        $display("Read Data (NAND): %b", read_data);

        read_address = 3'b011; #5;
        $display("Read Data (NOR): %b", read_data);

        $finish; // End simulation
    end
endmodule

DDCO_HACKATHON/alu_register.vcd
$date
	Wed Nov 20 13:55:14 2024
$end
$version
	Icarus Verilog
$end
$timescale
	1ps
$end
$scope module alu_register_tb $end
$var wire 8 ! read_data [7:0] $end
$var reg 8 " a [7:0] $end
$var reg 8 # b [7:0] $end
$var reg 1 $ clk $end
$var reg 2 % opcode [1:0] $end
$var reg 3 & read_address [2:0] $end
$var reg 3 ' write_address [2:0] $end
$var reg 1 ( write_enable $end
$scope module dut $end
$var wire 8 ) a [7:0] $end
$var wire 8 * b [7:0] $end
$var wire 1 $ clk $end
$var wire 2 + opcode [1:0] $end
$var wire 3 , read_address [2:0] $end
$var wire 3 - write_address [2:0] $end
$var wire 1 ( write_enable $end
$var wire 8 . read_data [7:0] $end
$var wire 8 / alu_result [7:0] $end
$scope module alu_inst $end
$var wire 8 0 a [7:0] $end
$var wire 8 1 b [7:0] $end
$var wire 2 2 opcode [1:0] $end
$var reg 8 3 result [7:0] $end
$upscope $end
$scope module register_file_inst $end
$var wire 1 $ clk $end
$var wire 3 4 read_address [2:0] $end
$var wire 3 5 write_address [2:0] $end
$var wire 8 6 write_data [7:0] $end
$var wire 1 ( write_enable $end
$var reg 8 7 read_data [7:0] $end
$upscope $end
$upscope $end
$upscope $end
$enddefinitions $end
$comment Show the parameter values. $end
$dumpall
$end
#0
$dumpvars
bx 7
b10001000 6
b0 5
bx 4
b10001000 3
b0 2
b11001100 1
b10101010 0
b10001000 /
bx .
b0 -
bx ,
b0 +
b11001100 *
b10101010 )
1(
b0 '
bx &
b0 %
0$
b11001100 #
b10101010 "
bx !
$end
#5000
1$
#10000
b11101110 /
b11101110 3
b11101110 6
0$
b1 '
b1 -
b1 5
b1 %
b1 +
b1 2
1(
#15000
1$
#20000
b1110111 /
b1110111 3
b1110111 6
0$
b10 '
b10 -
b10 5
b10 %
b10 +
b10 2
1(
#25000
1$
#30000
b10001 /
b10001 3
b10001 6
0$
b11 '
b11 -
b11 5
b11 %
b11 +
b11 2
1(
#35000
1$
#40000
b10001000 !
b10001000 .
b10001000 7
0$
b0 &
b0 ,
b0 4
0(
#45000
b11101110 !
b11101110 .
b11101110 7
1$
b1 &
b1 ,
b1 4
#50000
b1110111 !
b1110111 .
b1110111 7
0$
b10 &
b10 ,
b10 4
#55000
b10001 !
b10001 .
b10001 7
1$
b11 &
b11 ,
b11 4
