week2/question-1/sample_circuit.v
module sample_circuit (a,b,c,d,e);
    input a,b,c;
    output d,e;
    wire w1;

    and G1(w1,a,b);
    not G2(e,c);
    or G3(d,w1,e);
endmodule

week2/question-1/test_bench.v
module test_bench;
    
    reg a,b,c;
    wire d,e;

    sample_circuit M1(a,b,c,d,e);
    initial begin
        a = 0; b = 0; c = 0;
        #20
        a = 0; b = 0; c = 1;
        #20
        a = 0; b = 1; c = 0;
        #20
        a = 0; b = 1; c = 1;
        #20
        a = 1; b = 0; c = 0;
        #20
        a = 1; b = 0; c = 1;
        #20
        a = 1; b = 1; c = 0;
        #20
        a = 1; b = 1; c = 1;
    end

    initial begin
        $monitor($time, "a = %b, b = %b, c = %b, d = %b, e = %b", a, b, c, d, e);
    end

    initial begin
        $dumpfile("sample.vcd");
        $dumpvars(0, test_bench);
    end

endmodule

week2/question-1/sample.vcd
$date
	Thu Aug 29 15:05:23 2024
$end
$version
	Icarus Verilog
$end
$timescale
	1s
$end
$scope module test_bench $end
$var wire 1 ! e $end
$var wire 1 " d $end
$var reg 1 # a $end
$var reg 1 $ b $end
$var reg 1 % c $end
$scope module M1 $end
$var wire 1 # a $end
$var wire 1 $ b $end
$var wire 1 % c $end
$var wire 1 " d $end
$var wire 1 ! e $end
$var wire 1 & w1 $end
$upscope $end
$upscope $end
$enddefinitions $end
$comment Show the parameter values. $end
$dumpall
$end
#0
$dumpvars
0&
0%
0$
0#
1"
1!
$end
#20
0"
0!
1%
#40
1"
1!
0%
1$
#60
0"
0!
1%
#80
1"
1!
0%
0$
1#
#100
0"
0!
1%
#120
1"
1!
1&
0%
1$
#140
0!
1%
