week2/question-3/circuit.v
module circuit (A,B,C,D);
    
    input A,B,C;
    output D;

    wire w1,w2,w3;

    and G1(w1,B,C);
    or G2(w2,w1,A);
    and G3(w3,A,B);
    or G4(D,w2,w3);
endmodule

week2/question-3/test_bench.v
module test_bench;

    reg A,B,C;
    wire D;

    circuit M1(A,B,C,D);

    initial begin
        A = 0; B = 0; C = 0;
        #20
        A = 0; B = 0; C = 1;
        #20
        A = 0; B = 1; C = 0;
        #20
        A = 0; B = 1; C = 1;
        #20
        A = 1; B = 0; C = 1;
        #20
        A = 1; B = 0; C = 0;
        #20
        A = 1; B = 1; C = 0;
        #20
        A = 1; B = 1; C = 1;
    end

    initial begin
        $monitor($time, "a = %b, b = %b, c = %b, d = %b", A, B, C, D);
    end

    initial begin
        $dumpfile("sample.vcd");
        $dumpvars(0, test_bench);
    end
endmodule;

week2/question-3/sample.vcd
$date
	Thu Aug 29 15:05:47 2024
$end
$version
	Icarus Verilog
$end
$timescale
	1s
$end
$scope module test_bench $end
$var wire 1 ! D $end
$var reg 1 " A $end
$var reg 1 # B $end
$var reg 1 $ C $end
$scope module M1 $end
$var wire 1 " A $end
$var wire 1 # B $end
$var wire 1 $ C $end
$var wire 1 ! D $end
$var wire 1 % w1 $end
$var wire 1 & w2 $end
$var wire 1 ' w3 $end
$upscope $end
$upscope $end
$enddefinitions $end
$comment Show the parameter values. $end
$dumpall
$end
#0
$dumpvars
0'
0&
0%
0$
0#
0"
0!
$end
#20
1$
#40
0$
1#
#60
1!
1&
1%
1$
#80
0%
0#
1"
#100
0$
#120
1'
1#
#140
1%
1$
