week3/circuit3/fass.v
module fass(
    input wire [2:0] i1,
    input wire i2,
    output wire [2:0] sum1,
    output wire Cout1
);

    wire c;
    full_adder fa1 (i1[0], i2, 1'b0, sum1[0], c);
    full_adder fa2 (i1[1], 1'b0, c, sum1[1], c);
    full_adder fa3 (i1[2], 1'b0, c, sum1[2], Cout1);
endmodule

module full_adder(
    input wire a,
    input wire b,
    input wire cin,
    output wire sum,
    output wire cout
);

    assign sum = a ^ b ^ cin;
    assign cout = (a & b) | (a & cin) | (b & cin);
endmodule

week3/circuit3/fasstb.v
`timescale 1ns / 1ps

module fasstb;

    reg [2:0] i1;
    reg i2;
    wire [2:0] sum1;
    wire Cout1;

    fass dut (i1, i2, sum1, Cout1);

    initial begin
        $dumpfile("fass.vcd");
        $dumpvars(0, fasstb);

        // Test cases
        i1 = 3'b000; i2 = 1'b0; #10;
        i1 = 3'b001; i2 = 1'b0; #10;
        i1 = 3'b010; i2 = 1'b0; #10;
        i1 = 3'b011; i2 = 1'b0; #10;
        i1 = 3'b100; i2 = 1'b0; #10;
        i1 = 3'b101; i2 = 1'b0; #10;
        i1 = 3'b110; i2 = 1'b0; #10;
        i1 = 3'b111; i2 = 1'b0; #10;

        i1 = 3'b000; i2 = 1'b1; #10;
        i1 = 3'b001; i2 = 1'b1; #10;
        i1 = 3'b010; i2 = 1'b1; #10;
        i1 = 3'b011; i2 = 1'b1; #10;
        i1 = 3'b100; i2 = 1'b1; #10;
        i1 = 3'b101; i2 = 1'b1; #10;
        i1 = 3'b110; i2 = 1'b1; #10;
        i1 = 3'b111; i2 = 1'b1; #10;

        $finish;
    end

    initial begin
        $monitor("i1=%b, i2=%b, sum1=%b, Cout1=%b", i1, i2, sum1, Cout1);
    end

endmodule

week3/circuit3/fass.vcd
$date
	Thu Sep 12 20:41:38 2024
$end
$version
	Icarus Verilog
$end
$timescale
	1ps
$end
$scope module fasstb $end
$var wire 3 ! sum1 [2:0] $end
$var wire 1 " Cout1 $end
$var reg 3 # i1 [2:0] $end
$var reg 1 $ i2 $end
$scope module dut $end
$var wire 1 % c $end
$var wire 3 & i1 [2:0] $end
$var wire 1 $ i2 $end
$var wire 3 ' sum1 [2:0] $end
$var wire 1 " Cout1 $end
$scope module fa1 $end
$var wire 1 ( a $end
$var wire 1 $ b $end
$var wire 1 ) cin $end
$var wire 1 % cout $end
$var wire 1 * sum $end
$upscope $end
$scope module fa2 $end
$var wire 1 + a $end
$var wire 1 , b $end
$var wire 1 % cin $end
$var wire 1 % cout $end
$var wire 1 - sum $end
$upscope $end
$scope module fa3 $end
$var wire 1 . a $end
$var wire 1 / b $end
$var wire 1 % cin $end
$var wire 1 " cout $end
$var wire 1 0 sum $end
$upscope $end
$upscope $end
$upscope $end
$enddefinitions $end
$comment Show the parameter values. $end
$dumpall
$end
#0
$dumpvars
00
0/
0.
0-
0,
0+
0*
0)
0(
b0 '
b0 &
0%
0$
b0 #
0"
b0 !
$end
#10000
b1 !
b1 '
1*
1(
b1 #
b1 &
#20000
0*
b10 !
b10 '
1-
0(
1+
b10 #
b10 &
#30000
b11 !
b11 '
1*
1(
b11 #
b11 &
#40000
0*
0-
b100 !
b100 '
10
0(
0+
1.
b100 #
b100 &
#50000
b101 !
b101 '
1*
1(
b101 #
b101 &
#60000
0*
b110 !
b110 '
1-
0(
1+
b110 #
b110 &
#70000
b111 !
b111 '
1*
1(
b111 #
b111 &
#80000
0-
b1 !
b1 '
00
0(
0+
0.
1$
b0 #
b0 &
#90000
x-
x0
x%
bx0 !
bx0 '
0*
1(
b1 #
b1 &
#100000
bx1 !
bx1 '
1*
0(
1+
b10 #
b10 &
#110000
bx0 !
bx0 '
0*
1(
b11 #
b11 &
#120000
0-
10
0%
0"
b101 !
b101 '
1*
0(
0+
1.
b100 #
b100 &
#130000
x"
x-
x0
x%
bx0 !
bx0 '
0*
1(
b101 #
b101 &
#140000
bx1 !
bx1 '
1*
0(
1+
b110 #
b110 &
#150000
bx0 !
bx0 '
0*
1(
b111 #
b111 &
