project/johnson_counter.v
module johnson_counter (
    input clk,
    input rst_n,        // Active-low reset
    output reg [3:0] q  // 4-bit output
);
    always @(posedge clk or negedge rst_n) begin
        if (!rst_n)
            q <= 4'b0000;  // Initialize to zero
        else
            q <= {~q[3], q[3:1]};  // Shift left and feed complement of MSB
    end
endmodule

project/ring_counter.v
module ring_counter (
    input wire clk,      // Clock signal
    input wire rst_n,    // Active-low reset signal
    output reg [3:0] q   // 4-bit output for Ring Counter
);

    always @(posedge clk or negedge rst_n) begin
        if (!rst_n)
            q <= 4'b1000;  // On reset, initialize the counter to "1000" with one '1'
        else
            q <= {q[2:0], q[3]};  // Circular left shift (rotate)
    end

endmodule

project/counter_control.v
module counter_control(
    input wire clk,
    input wire rst_n,    // Active-low reset signal
    input wire mode,     // 0 for Ring Counter, 1 for Johnson Counter
    output wire [3:0] q
);

    wire [3:0] q_ring;    // Wire for Ring Counter output
    wire [3:0] q_johnson; // Wire for Johnson Counter output

    // Instantiate Ring Counter
    ring_counter rc (
        .clk(clk),
        .rst_n(rst_n),   // Match port names (rst_n for active-low reset)
        .q(q_ring)
    );

    // Instantiate Johnson Counter
    johnson_counter jc (
        .clk(clk),
        .rst_n(rst_n),   // Match port names (rst_n for active-low reset)
        .q(q_johnson)
    );

    // Control logic: Mux between Ring Counter and Johnson Counter outputs
    assign q = (mode == 0) ? q_ring : q_johnson;

endmodule

project/tb_counter_control.v
module tb_counter_control;

    reg clk;
    reg rst_n;       // Active-low reset
    reg mode;
    wire [3:0] q;

    // Instantiate the counter control module
    counter_control uut (
        .clk(clk),
        .rst_n(rst_n),   // Active-low reset
        .mode(mode),
        .q(q)
    );

    // Generate clock signal
    always #5 clk = ~clk;

    // Testbench stimulus
    initial begin
        // Initialize inputs
        clk = 0;
        rst_n = 0;  // Assert reset (active-low)
        mode = 0;   // Start with Ring Counter mode

        // Hold reset for a few clock cycles
        #10 rst_n = 1;  // De-assert reset

        // Switch to Johnson Counter after some time
        #50 mode = 1;

        // Run simulation for a while
        #100 $finish;
    end

    // Monitor outputs: Print values at each change
    initial begin
        $monitor("Time = %0t | mode = %b | q = %b", $time, mode, q);
    end

    // Dump waveforms for debugging
    initial begin
        $dumpfile("dumpfile.vcd");
        $dumpvars(0, tb_counter_control);
    end

endmodule

project/dumpfile.vcd
$date
	Sat Oct 19 22:49:03 2024
$end
$version
	Icarus Verilog
$end
$timescale
	1s
$end
$scope module tb_counter_control $end
$var wire 4 ! q [3:0] $end
$var reg 1 " clk $end
$var reg 1 # mode $end
$var reg 1 $ rst_n $end
$scope module uut $end
$var wire 1 " clk $end
$var wire 1 # mode $end
$var wire 1 $ rst_n $end
$var wire 4 % q_ring [3:0] $end
$var wire 4 & q_johnson [3:0] $end
$var wire 4 ' q [3:0] $end
$scope module jc $end
$var wire 1 " clk $end
$var wire 1 $ rst_n $end
$var reg 4 ( q [3:0] $end
$upscope $end
$scope module rc $end
$var wire 1 " clk $end
$var wire 1 $ rst_n $end
$var reg 4 ) q [3:0] $end
$upscope $end
$upscope $end
$upscope $end
$enddefinitions $end
$comment Show the parameter values. $end
$dumpall
$end
#0
$dumpvars
b1000 )
b0 (
b1000 '
b0 &
b1000 %
0$
0#
0"
b1000 !
$end
#5
1"
#10
0"
1$
#15
b1 !
b1 '
b1 %
b1 )
b1000 &
b1000 (
1"
#20
0"
#25
b10 !
b10 '
b100 &
b100 (
b10 %
b10 )
1"
#30
0"
#35
b100 !
b100 '
b100 %
b100 )
b1010 &
b1010 (
1"
#40
0"
#45
b1000 !
b1000 '
b101 &
b101 (
b1000 %
b1000 )
1"
#50
0"
#55
b1 !
b1 '
b1 %
b1 )
b1010 &
b1010 (
1"
#60
b1010 !
b1010 '
0"
1#
#65
b101 !
b101 '
b101 &
b101 (
b10 %
b10 )
1"
#70
0"
#75
b1010 !
b1010 '
b100 %
b100 )
b1010 &
b1010 (
1"
#80
0"
#85
b101 !
b101 '
b101 &
b101 (
b1000 %
b1000 )
1"
#90
0"
#95
b1010 !
b1010 '
b1 %
b1 )
b1010 &
b1010 (
1"
#100
0"
#105
b101 !
b101 '
b101 &
b101 (
b10 %
b10 )
1"
#110
0"
#115
b1010 !
b1010 '
b100 %
b100 )
b1010 &
b1010 (
1"
#120
0"
#125
b101 !
b101 '
b101 &
b101 (
b1000 %
b1000 )
1"
#130
0"
#135
b1010 !
b1010 '
b1 %
b1 )
b1010 &
b1010 (
1"
#140
0"
#145
b101 !
b101 '
b101 &
b101 (
b10 %
b10 )
1"
#150
0"
#155
b1010 !
b1010 '
b100 %
b100 )
b1010 &
b1010 (
1"
