project/counter_control.v
module counter_control(
    input clk,
    input rst_n,        // Active-low reset
    input mode,         // Mode selection: 0 for Ring Counter, 1 for Johnson Counter
    output reg [3:0] q  // 4-bit output
);

    // Internal registers to store the state of the counters
    reg [3:0] ring_counter;
    reg [3:0] johnson_counter;

    always @(posedge clk or negedge rst_n) begin
        if (!rst_n) begin
            // Reset both counters to zero
            ring_counter <= 4'b0001;  // Set initial state for Ring Counter to avoid undefined state
            johnson_counter <= 4'b0000;  // Reset Johnson Counter
        end else begin
            if (mode == 0) begin
                // Ring Counter Logic: Shift left, MSB is fed back to LSB
                ring_counter <= {ring_counter[2:0], ring_counter[3]};
                q <= ring_counter;  // Output the ring counter
            end else begin
                // Johnson Counter Logic: Complement MSB and feed it to LSB
                johnson_counter[3] <= ~johnson_counter[0];
                johnson_counter[2:0] <= johnson_counter[3:1];
                q <= johnson_counter;  // Output the johnson counter
            end
        end
    end

endmodule

project/tb_counter_control.v
module tb_counter_control;

    reg clk;
    reg rst_n;       // Active-low reset
    reg mode;
    wire [3:0] q;

    // Instantiate the counter control module
    counter_control uut (
        .clk(clk),
        .rst_n(rst_n),   // Active-low reset
        .mode(mode),
        .q(q)
    );

    // Generate clock signal
    always #5 clk = ~clk;

    // Testbench stimulus
    initial begin
        // Initialize inputs
        clk = 0;
        rst_n = 0;  // Assert reset (active-low)
        mode = 0;   // Start with Ring Counter mode

        // Hold reset for a few clock cycles
        #10 rst_n = 1;  // De-assert reset

        // Switch to Johnson Counter after some time
        #50 mode = 1;

        // Run simulation for a while
        #100 $finish;
    end

    // Monitor outputs: Print values at each change
    initial begin
        $monitor("Time = %0t | mode = %b | q = %b", $time, mode, q);
    end

    // Dump waveforms for debugging
    initial begin
        $dumpfile("dumpfile.vcd");
        $dumpvars(0, tb_counter_control);
    end

endmodule

project/dumpfile.vcd
$date
	Wed Nov 20 20:14:15 2024
$end
$version
	Icarus Verilog
$end
$timescale
	1s
$end
$scope module tb_counter_control $end
$var wire 4 ! q [3:0] $end
$var reg 1 " clk $end
$var reg 1 # mode $end
$var reg 1 $ rst_n $end
$scope module uut $end
$var wire 1 " clk $end
$var wire 1 # mode $end
$var wire 1 $ rst_n $end
$var reg 4 % johnson_counter [3:0] $end
$var reg 4 & q [3:0] $end
$var reg 4 ' ring_counter [3:0] $end
$upscope $end
$upscope $end
$enddefinitions $end
$comment Show the parameter values. $end
$dumpall
$end
#0
$dumpvars
b1 '
bx &
b0 %
0$
0#
0"
bx !
$end
#5
1"
#10
0"
1$
#15
b1 !
b1 &
b10 '
1"
#20
0"
#25
b10 !
b10 &
b100 '
1"
#30
0"
#35
b100 !
b100 &
b1000 '
1"
#40
0"
#45
b1000 !
b1000 &
b1 '
1"
#50
0"
#55
b1 !
b1 &
b10 '
1"
#60
0"
1#
#65
b0 !
b0 &
b1000 %
1"
#70
0"
#75
b1000 !
b1000 &
b1100 %
1"
#80
0"
#85
b1100 !
b1100 &
b1110 %
1"
#90
0"
#95
b1110 !
b1110 &
b1111 %
1"
#100
0"
#105
b1111 !
b1111 &
b111 %
1"
#110
0"
#115
b111 !
b111 &
b11 %
1"
#120
0"
#125
b11 !
b11 &
b1 %
1"
#130
0"
#135
b1 !
b1 &
b0 %
1"
#140
0"
#145
b0 !
b0 &
b1000 %
1"
#150
0"
#155
b1000 !
b1000 &
b1100 %
1"
#160
0"
#165
b1100 !
b1100 &
b1110 %
1"
#170
0"
#175
b1110 !
b1110 &
b1111 %
1"
#180
0"
#185
b1111 !
b1111 &
b111 %
1"
#190
0"
#195
b111 !
b111 &
b11 %
1"
#200
0"
#205
b11 !
b11 &
b1 %
1"
#210
0"
#215
b1 !
b1 &
b0 %
1"
#220
0"
#225
b0 !
b0 &
b1000 %
1"
#230
0"
#235
b1000 !
b1000 &
b1100 %
1"
#240
0"
#245
b1100 !
b1100 &
b1110 %
1"
#250
0"
#255
b1110 !
b1110 &
b1111 %
1"
